Django_PO-0.0.1.dist-info/DESCRIPTION.rst
Django_PO-0.0.1.dist-info/METADATA
Django_PO-0.0.1.dist-info/RECORD
Django_PO-0.0.1.dist-info/WHEEL
Django_PO-0.0.1.dist-info/metadata.json
Django_PO-0.0.1.dist-info/top_level.txt
django_po/__init__.py
django_po/admin.py
django_po/apps.py
django_po/models.py
django_po/tests.py
django_po/views.py
django_po/management/__init__.py
django_po/management/commands/__init__.py
django_po/management/commands/export_po.py
